pymarktex/__init__.py
pymarktex/figures/__init__.py
pymarktex/templates/__init__.py
pymarktex-1.1.3.data/scripts/pymarktex
pymarktex-1.1.3.dist-info/LICENSE.txt
pymarktex-1.1.3.dist-info/METADATA
pymarktex-1.1.3.dist-info/WHEEL
pymarktex-1.1.3.dist-info/top_level.txt
pymarktex-1.1.3.dist-info/RECORD
