Metadata-Version: 2.1
Name: pymarktex
Version: 1.1.3
Summary: Will convert a markdown text file to a fancy PDF document
Home-page: http://github.com/xapple/pymarktex/
Author: Lucas Sinclair
Author-email: lucas.sinclair@me.com
License: MIT
Platform: UNKNOWN
Requires-Dist: autopaths
Requires-Dist: plumbing
Requires-Dist: sh
Requires-Dist: pystache
